.gitignore
CHANGES.txt
CONTRIBUTORS.txt
COPYRIGHT.txt
LICENSE.txt
README.txt
setup.cfg
setup.py
tox.ini
docs/.gitignore
docs/Makefile
docs/conf.py
docs/glossary.rst
docs/index.rst
docs/_static/exclaim.png
docs/_static/exclaim_color.png
docs/_static/info.png
docs/_static/info_color.png
docs/_static/onebit_36.png
docs/_static/onebit_38.png
docs/_static/pyramid.png
docs/_static/pyramid_epub.css
pyramid_formish/__init__.py
pyramid_formish/fix_formish_imports.py
pyramid_formish/meta.zcml
pyramid_formish/zcml.py
pyramid_formish.egg-info/PKG-INFO
pyramid_formish.egg-info/SOURCES.txt
pyramid_formish.egg-info/dependency_links.txt
pyramid_formish.egg-info/entry_points.txt
pyramid_formish.egg-info/not-zip-safe
pyramid_formish.egg-info/requires.txt
pyramid_formish.egg-info/top_level.txt
pyramid_formish/templates/zpt/formish/field/main.html
pyramid_formish/templates/zpt/formish/form/fields.html
pyramid_formish/templates/zpt/formish/form/main.html
pyramid_formish/templates/zpt/formish/sequence/main.html
pyramid_formish/templates/zpt/formish/structure/main.html
pyramid_formish/templates/zpt/formish/test/test.html
pyramid_formish/templates/zpt/formish/widgets/Checkbox/widget.html
pyramid_formish/templates/zpt/formish/widgets/CheckboxMultiChoice/readonly.html
pyramid_formish/templates/zpt/formish/widgets/CheckboxMultiChoice/widget.html
pyramid_formish/templates/zpt/formish/widgets/CheckboxMultiChoiceTree/readonly.html
pyramid_formish/templates/zpt/formish/widgets/CheckboxMultiChoiceTree/widget.html
pyramid_formish/templates/zpt/formish/widgets/CheckedInput/readonly.html
pyramid_formish/templates/zpt/formish/widgets/CheckedInput/widget.html
pyramid_formish/templates/zpt/formish/widgets/CheckedPassword/readonly.html
pyramid_formish/templates/zpt/formish/widgets/CheckedPassword/widget.html
pyramid_formish/templates/zpt/formish/widgets/DateParts/readonly.html
pyramid_formish/templates/zpt/formish/widgets/DateParts/widget.html
pyramid_formish/templates/zpt/formish/widgets/FileUpload/widget.html
pyramid_formish/templates/zpt/formish/widgets/Grid/readonly.html
pyramid_formish/templates/zpt/formish/widgets/Grid/widget.html
pyramid_formish/templates/zpt/formish/widgets/Hidden/readonly.html
pyramid_formish/templates/zpt/formish/widgets/Hidden/widget.html
