Metadata-Version: 1.0
Name: pyramid-formish
Version: 0.1
Summary: Formish bindings and helpers for Pyramid web framework
Home-page: http://www.repoze.org
Author: Chris McDonough, Agendaless Consulting
Author-email: repoze-dev@lists.repoze.org
License: BSD-derived (http://www.repoze.org/LICENSE.txt)
Keywords: web formish formgen bfg pyramid
Platform: UNKNOWN
Classifier: Intended Audience :: Developers
Classifier: Programming Language :: Python
Classifier: Topic :: Internet :: WWW/HTTP
Classifier: Topic :: Internet :: WWW/HTTP :: Dynamic Content
